liquid/__init__.py
liquid/analyze_tags.py
liquid/ast.py
liquid/context.py
liquid/environment.py
liquid/exceptions.py
liquid/expression.py
liquid/filter.py
liquid/lex.py
liquid/limits.py
liquid/loader.py
liquid/messages.py
liquid/mode.py
liquid/output.py
liquid/parser.py
liquid/py.typed
liquid/span.py
liquid/static_analysis.py
liquid/stream.py
liquid/stringify.py
liquid/tag.py
liquid/template.py
liquid/token.py
liquid/undefined.py
liquid/builtin/__init__.py
liquid/builtin/content.py
liquid/builtin/illegal.py
liquid/builtin/output.py
liquid/builtin/drops/__init__.py
liquid/builtin/drops/drops.py
liquid/builtin/expressions/__init__.py
liquid/builtin/expressions/_tokenize.py
liquid/builtin/expressions/arguments.py
liquid/builtin/expressions/filtered.py
liquid/builtin/expressions/logical.py
liquid/builtin/expressions/loop.py
liquid/builtin/expressions/path.py
liquid/builtin/expressions/primitive.py
liquid/builtin/filters/__init__.py
liquid/builtin/filters/array.py
liquid/builtin/filters/extra.py
liquid/builtin/filters/math.py
liquid/builtin/filters/misc.py
liquid/builtin/filters/string.py
liquid/builtin/loaders/__init__.py
liquid/builtin/loaders/caching_file_system_loader.py
liquid/builtin/loaders/choice_loader.py
liquid/builtin/loaders/dict_loader.py
liquid/builtin/loaders/file_system_loader.py
liquid/builtin/loaders/mixins.py
liquid/builtin/loaders/package_loader.py
liquid/builtin/tags/__init__.py
liquid/builtin/tags/assign_tag.py
liquid/builtin/tags/capture_tag.py
liquid/builtin/tags/case_tag.py
liquid/builtin/tags/comment_tag.py
liquid/builtin/tags/cycle_tag.py
liquid/builtin/tags/decrement_tag.py
liquid/builtin/tags/doc_tag.py
liquid/builtin/tags/echo_tag.py
liquid/builtin/tags/for_tag.py
liquid/builtin/tags/if_tag.py
liquid/builtin/tags/ifchanged_tag.py
liquid/builtin/tags/include_tag.py
liquid/builtin/tags/increment_tag.py
liquid/builtin/tags/inline_comment_tag.py
liquid/builtin/tags/liquid_tag.py
liquid/builtin/tags/render_tag.py
python_liquid-2.0.2.dist-info/METADATA
python_liquid-2.0.2.dist-info/WHEEL
python_liquid-2.0.2.dist-info/licenses/LICENSE
python_liquid-2.0.2.dist-info/RECORD
