Metadata-Version: 2.4
Name: python-liquid
Version: 2.0.2
Summary: A Python engine for the Liquid template language.
Project-URL: Change Log, https://github.com/jg-rp/liquid/blob/main/CHANGES.md
Project-URL: Documentation, https://jg-rp.github.io/liquid/
Project-URL: Homepage, https://jg-rp.github.io/liquid/
Project-URL: Issue Tracker, https://github.com/jg-rp/liquid/issues
Project-URL: Source Code, https://github.com/jg-rp/liquid
Author-email: James Prior <jamesgr.prior@gmail.com>
License-Expression: MIT
License-File: LICENSE
Classifier: Development Status :: 5 - Production/Stable
Classifier: Intended Audience :: Developers
Classifier: License :: OSI Approved :: MIT License
Classifier: Programming Language :: Python :: 3
Classifier: Programming Language :: Python :: 3.9
Classifier: Programming Language :: Python :: 3.10
Classifier: Programming Language :: Python :: 3.11
Classifier: Programming Language :: Python :: 3.12
Classifier: Programming Language :: Python :: 3.13
Classifier: Programming Language :: Python :: Implementation :: CPython
Classifier: Programming Language :: Python :: Implementation :: PyPy
Requires-Python: >=3.7
Requires-Dist: babel>=2
Requires-Dist: markupsafe>=3
Requires-Dist: python-dateutil>=2.8.1
Requires-Dist: pytz
